.coveragerc
.gitattributes
.gitignore
.travis.yml
CHANGES
MANIFEST.in
README.rst
TODO
Yaybu.wpr
nose2.cfg
requirements.txt
setup.py
Yaybu.egg-info/PKG-INFO
Yaybu.egg-info/SOURCES.txt
Yaybu.egg-info/dependency_links.txt
Yaybu.egg-info/entry_points.txt
Yaybu.egg-info/not-zip-safe
Yaybu.egg-info/requires.txt
Yaybu.egg-info/top_level.txt
yaybu/__init__.py
yaybu/base.py
yaybu/changesource.py
yaybu/dns.py
yaybu/error.py
yaybu/heroku.py
yaybu/i18n.py
yaybu/loadbalancer.py
yaybu/minidns.py
yaybu/printer.py
yaybu/static.py
yaybu/changes/__init__.py
yaybu/changes/base.py
yaybu/changes/metadata.py
yaybu/compute/__init__.py
yaybu/compute/bigv.py
yaybu/compute/docker.py
yaybu/compute/metadata.py
yaybu/compute/part.py
yaybu/compute/vmware.py
yaybu/core/__init__.py
yaybu/core/argument.py
yaybu/core/command.py
yaybu/core/config.py
yaybu/core/error.py
yaybu/core/main.py
yaybu/core/policy.py
yaybu/core/state.py
yaybu/core/util.py
yaybu/provisioner/__init__.py
yaybu/provisioner/event.py
yaybu/provisioner/part.py
yaybu/provisioner/provider.py
yaybu/provisioner/resource.py
yaybu/provisioner/changes/__init__.py
yaybu/provisioner/changes/attributes.py
yaybu/provisioner/changes/directory.py
yaybu/provisioner/changes/execute.py
yaybu/provisioner/changes/file.py
yaybu/provisioner/providers/__init__.py
yaybu/provisioner/providers/apt.py
yaybu/provisioner/providers/execute.py
yaybu/provisioner/providers/git.py
yaybu/provisioner/providers/group.py
yaybu/provisioner/providers/mercurial.hgext
yaybu/provisioner/providers/mercurial.py
yaybu/provisioner/providers/mount.py
yaybu/provisioner/providers/mounted.py
yaybu/provisioner/providers/patch.py
yaybu/provisioner/providers/subversion.py
yaybu/provisioner/providers/user.py
yaybu/provisioner/providers/filesystem/__init__.py
yaybu/provisioner/providers/filesystem/directory.py
yaybu/provisioner/providers/filesystem/files.py
yaybu/provisioner/providers/filesystem/link.py
yaybu/provisioner/providers/service/__init__.py
yaybu/provisioner/providers/service/lsb.py
yaybu/provisioner/providers/service/simple.py
yaybu/provisioner/providers/service/simulated.py
yaybu/provisioner/providers/service/upstart.py
yaybu/provisioner/providers/service/utils.py
