Metadata-Version: 1.0
Name: Yaybu
Version: 3.1.1
Summary: Server deployment and configuration management in Python
Home-page: http://yaybu.com/
Author: Isotoma Limited
Author-email: support@isotoma.com
License: Apache Software License
Platform: UNKNOWN
Classifier: Intended Audience :: System Administrators
Classifier: Operating System :: POSIX
Classifier: License :: OSI Approved :: Apache Software License
